celery_progress/__init__.py
celery_progress/backend.py
celery_progress/tasks.py
celery_progress/urls.py
celery_progress/views.py
celery_progress/static/celery_progress/celery_progress.js
celery_progress/static/celery_progress/websockets.js
celery_progress/websockets/__init__.py
celery_progress/websockets/backend.py
celery_progress/websockets/consumers.py
celery_progress/websockets/routing.py
celery_progress/websockets/tasks.py
celery_progress-0.4.data/data/static/celery_progress/celery_progress.js
celery_progress-0.4.data/data/static/celery_progress/websockets.js
celery_progress-0.4.dist-info/LICENSE
celery_progress-0.4.dist-info/METADATA
celery_progress-0.4.dist-info/WHEEL
celery_progress-0.4.dist-info/top_level.txt
celery_progress-0.4.dist-info/RECORD
