Metadata-Version: 2.1
Name: celery-progress
Version: 0.4
Summary: Drop in, configurable, dependency-free progress bars for your Django/Celery applications.
Home-page: https://github.com/czue/celery-progress
Author: Cory Zue
Author-email: cory@coryzue.com
License: MIT License
Classifier: Environment :: Web Environment
Classifier: Framework :: Django
Classifier: Framework :: Django :: 2.0
Classifier: Framework :: Django :: 2.1
Classifier: Framework :: Django :: 2.2
Classifier: Framework :: Django :: 3.0
Classifier: Framework :: Django :: 3.1
Classifier: Framework :: Django :: 3.2
Classifier: Framework :: Django :: 4.0
Classifier: Framework :: Django :: 4.1
Classifier: Intended Audience :: Developers
Classifier: License :: OSI Approved :: MIT License
Classifier: Operating System :: OS Independent
Classifier: Programming Language :: Python
Classifier: Programming Language :: Python :: 3.5
Classifier: Programming Language :: Python :: 3.6
Classifier: Programming Language :: Python :: 3.7
Classifier: Programming Language :: Python :: 3.8
Classifier: Programming Language :: Python :: 3.9
Classifier: Programming Language :: Python :: 3.10
Classifier: Programming Language :: Python :: 3.11
Classifier: Topic :: Internet :: WWW/HTTP
Classifier: Topic :: Internet :: WWW/HTTP :: Dynamic Content
License-File: LICENSE
Provides-Extra: websockets
Requires-Dist: channels; extra == "websockets"
Provides-Extra: redis
Requires-Dist: channels_redis; extra == "redis"
Provides-Extra: rabbitmq
Requires-Dist: channels_rabbitmq; extra == "rabbitmq"
